TextSimila/__init__.py
TextSimila/preprocess.py
TextSimila/text_sim_reco.py
example/__init__.py
example/exe.py
TextSimila-0.0.6.dist-info/LICENSE
TextSimila-0.0.6.dist-info/METADATA
TextSimila-0.0.6.dist-info/WHEEL
TextSimila-0.0.6.dist-info/top_level.txt
TextSimila-0.0.6.dist-info/RECORD
